223/sex.vhdl
library ieee;
use ieee.std_logic_1164.all;
use ieee.numeric_std.all;
-- Control FSM + one digit in base 223 (0 .. 222).
-- inc_i must be high for exactly one clk_i cycle (single-cycle pulse).
entity base223_fsm is
  port (
    clk_i   : in  std_logic;
    rst_i   : in  std_logic;
    clr_i   : in  std_logic;              -- synchronous clear -> digit 0, state CLEAR
    run_i   : in  std_logic;              -- 0 = paused, 1 = may count
    inc_i   : in  std_logic;              -- pulse: +1 mod 223
    digit_o : out unsigned(7 downto 0);  -- current value 0 .. 222
    wrap_o  : out std_logic               -- 1 for one cycle when 222 -> 0
  );
end entity base223_fsm;
architecture rtl of base223_fsm is
  type state_t is (ST_CLEAR, ST_RUN, ST_PAUSE);
  signal state_r, state_x : state_t;
  signal digit_r, digit_x : unsigned(7 downto 0);
  signal wrap_x, wrap_r   : std_logic;
begin
  comb : process (all) is
  begin
    state_x <= state_r;
    digit_x <= digit_r;
    wrap_x  <= '0';
    case state_r is
      when ST_CLEAR =>
        digit_x <= (others => '0');
        if run_i = '1' then
          state_x <= ST_RUN;
        else
          state_x <= ST_PAUSE;
        end if;
      when ST_PAUSE =>
        if clr_i = '1' then
          state_x <= ST_CLEAR;
        elsif run_i = '1' then
          state_x <= ST_RUN;
        end if;
      when ST_RUN =>
        if clr_i = '1' then
          state_x <= ST_CLEAR;
        elsif run_i = '0' then
          state_x <= ST_PAUSE;
        elsif inc_i = '1' then
          if digit_r = to_unsigned(222, digit_r'length) then
            digit_x <= (others => '0');
            wrap_x  <= '1';
          else
            digit_x <= digit_r + 1;
          end if;
        end if;
    end case;
  end process comb;
  seq : process (clk_i) is
  begin
    if rising_edge(clk_i) then
      if rst_i = '1' then
        state_r <= ST_CLEAR;
        digit_r <= (others => '0');
        wrap_r  <= '0';
      else
        state_r <= state_x;
        digit_r <= digit_x;
        wrap_r  <= wrap_x;
      end if;
    end if;
  end process seq;
  digit_o <= digit_r;
  wrap_o  <= wrap_r;
end architecture rtl;

223/tb_sex.vhdl
-- Testbench: replay MMIO writes from `thecode` (RISC-V sb to 0x4000_0000)
-- Byte 2 -> pause (run_i = '0'); byte 4 -> clear (clr_i pulse for one cycle).
library ieee;
use ieee.std_logic_1164.all;
use ieee.numeric_std.all;

entity tb_sex is
end entity tb_sex;

architecture sim of tb_sex is
  constant ctrl_base : natural := 16#4000_0000#;

  signal clk     : std_logic := '0';
  signal rst     : std_logic := '1';
  signal clr_i   : std_logic := '0';
  signal run_i   : std_logic := '0';
  signal inc_i   : std_logic := '0';
  signal digit_o : unsigned(7 downto 0);
  signal wrap_o  : std_logic;

  constant clk_period : time := 10 ns;

  procedure mmio_sb (
    signal clock : in std_logic;
    signal run_s : out std_logic;
    signal clr_s : out std_logic;
    addr         : natural;
    byte         : natural) is
  begin
    wait until rising_edge(clock);
    case byte is
      when 1 =>
        run_s <= '1';
        clr_s <= '0';
      when 2 =>
        run_s <= '0';
        clr_s <= '0';
      when 4 =>
        clr_s <= '1';
      when others =>
        null;
    end case;
    wait until rising_edge(clock);
    clr_s <= '0';
  end procedure;

  -- Single-cycle inc_i pulse: high is sampled on one rising_edge(clk).
  procedure pulse_inc (signal clock : in std_logic; signal inc_s : out std_logic) is
  begin
    wait until rising_edge(clock);
    inc_s <= '1';
    wait until rising_edge(clock);
    inc_s <= '0';
    wait until rising_edge(clock);
  end procedure;

  procedure snapshot (constant msg : in string) is
  begin
    report msg & " | digit_o=" & integer'image(to_integer(digit_o))
      & " wrap_o=" & std_logic'image(wrap_o)
      severity note;
  end procedure;

begin

  clk <= not clk after clk_period / 2;

  dut : entity work.base223_fsm
    port map (
      clk_i   => clk,
      rst_i   => rst,
      clr_i   => clr_i,
      run_i   => run_i,
      inc_i   => inc_i,
      digit_o => digit_o,
      wrap_o  => wrap_o);

  stim : process is
  begin
    inc_i <= '0';
    clr_i <= '0';
    run_i <= '0';
    rst   <= '1';
    wait for clk_period * 2;
    rst <= '0';
    wait for clk_period * 2;
    snapshot("after reset deassert");

    report "MMIO sb @0x40000000 byte 1 (run)" severity note;
    mmio_sb(clk, run_i, clr_i, ctrl_base, 1);
    snapshot("after run (sb 1)");

    for k in 1 to 3 loop
      report "inc_i pulse #" & integer'image(k) severity note;
      pulse_inc(clk, inc_i);
      snapshot("after inc pulse #" & integer'image(k));
    end loop;

    -- Mirrors thecode (thecode skips run + inc; stores only 2 then 4)
    -- li x10, 0x40000000  — implicit in mmio_sb addr
    report "MMIO sb @0x40000000 byte 2 (pause)" severity note;
    mmio_sb(clk, run_i, clr_i, ctrl_base, 2);
    snapshot("after pause (sb 2)");

    report "MMIO sb @0x40000000 byte 4 (clear pulse)" severity note;
    mmio_sb(clk, run_i, clr_i, ctrl_base, 4);
    -- Sample after DUT seq runs (avoid reading digit_o in same delta as clk edge)
    wait until rising_edge(clk);
    wait until falling_edge(clk);
    snapshot("after clear (sb 4)");

    wait for clk_period * 5;
    snapshot("before finish");
    std.env.finish;
  end process stim;

end architecture sim;

223/tb_sex.vcd
$date
  Mon Mar 23 17:46:58 2026
$end
$version
  GHDL v0
$end
$timescale
  1 fs
$end
$scope module standard $end
$upscope $end
$scope module textio $end
$upscope $end
$scope module std_logic_1164 $end
$upscope $end
$scope module numeric_std $end
$upscope $end
$scope module env $end
$upscope $end
$scope module tb_sex $end
$var reg 1 ! clk $end
$var reg 1 " rst $end
$var reg 1 # clr_i $end
$var reg 1 $ run_i $end
$var reg 1 % inc_i $end
$var reg 8 & digit_o[7:0] $end
$var reg 1 ' wrap_o $end
$scope module dut $end
$var reg 1 ( clk_i $end
$var reg 1 ) rst_i $end
$var reg 1 * clr_i $end
$var reg 1 + run_i $end
$var reg 1 , inc_i $end
$var reg 8 - digit_o[7:0] $end
$var reg 1 . wrap_o $end
$comment state_r is not handled $end
$comment state_x is not handled $end
$var reg 8 / digit_r[7:0] $end
$var reg 8 0 digit_x[7:0] $end
$var reg 1 1 wrap_x $end
$var reg 1 2 wrap_r $end
$upscope $end
$upscope $end
$enddefinitions $end
#0
0!
1"
0#
0$
0%
bUUUUUUUU &
U'
0(
1)
0*
0+
0,
bUUUUUUUU -
U.
bUUUUUUUU /
b00000000 0
01
U2
#5000000
1!
b00000000 &
0'
1(
b00000000 -
0.
b00000000 /
02
#10000000
0!
0(
#15000000
1!
1(
#20000000
0!
0"
0(
0)
#25000000
1!
1(
#30000000
0!
0(
#35000000
1!
1(
#40000000
0!
0(
#45000000
1!
1$
1(
1+
#50000000
0!
0(
#55000000
1!
1(
#60000000
0!
0(
#65000000
1!
1%
1(
1,
b00000001 0
#70000000
0!
0(
#75000000
1!
0%
b00000001 &
1(
0,
b00000001 -
b00000001 /
#80000000
0!
0(
#85000000
1!
1(
#90000000
0!
0(
#95000000
1!
1%
1(
1,
b00000010 0
#100000000
0!
0(
#105000000
1!
0%
b00000010 &
1(
0,
b00000010 -
b00000010 /
#110000000
0!
0(
#115000000
1!
1(
#120000000
0!
0(
#125000000
1!
1%
1(
1,
b00000011 0
#130000000
0!
0(
#135000000
1!
0%
b00000011 &
1(
0,
b00000011 -
b00000011 /
#140000000
0!
0(
#145000000
1!
1(
#150000000
0!
0(
#155000000
1!
0$
1(
0+
#160000000
0!
0(
#165000000
1!
1(
#170000000
0!
0(
#175000000
1!
1#
1(
1*
#180000000
0!
0(
#185000000
1!
0#
1(
0*
b00000000 0
#190000000
0!
0(
#195000000
1!
b00000000 &
1(
b00000000 -
b00000000 /
